Metadata-Version: 2.1
Name: Quart-Session-OpenID
Version: 1.0.3
Summary: Add identity providers to your Quart application
Home-page: https://github.com/sanderfoobar/quart-session-openid
Author: Sander
Author-email: sander@sanderf.nl
License: UNKNOWN
Platform: any
Classifier: Environment :: Web Environment
Classifier: Intended Audience :: Developers
Classifier: Operating System :: OS Independent
Classifier: Programming Language :: Python :: 3
Classifier: Programming Language :: Python :: 3.7
Classifier: Programming Language :: Python :: 3.8
Classifier: License :: OSI Approved :: BSD License
Classifier: Topic :: Internet :: WWW/HTTP :: Dynamic Content
Classifier: Topic :: Software Development :: Libraries :: Python Modules
Provides-Extra: dotenv
License-File: LICENSE
